{
  "name": "roq/okx/protocol/json/AccountItem",
  "type": "dictionary",
  "values": [
    {
      "name": "availBal",
      "type": "std/double"
    },
    {
      "name": "availEq",
      "type": "std/double"
    },
    {
      "name": "cashBal",
      "type": "std/double"
    },
    {
      "name": "ccy",
      "type": "std/string_view"
    },
    {
      "name": "coinUsdPrice",
      "type": "std/double"
    },
    {
      "name": "crossLiab",
      "type": "std/double"
    },
    {
      "name": "disEq",
      "type": "std/double"
    },
    {
      "name": "eq",
      "type": "std/double"
    },
    {
      "name": "eqUsd",
      "type": "std/double"
    },
    {
      "name": "frozenBal",
      "type": "std/double"
    },
    {
      "name": "interest",
      "type": "std/double"
    },
    {
      "name": "isoEq",
      "type": "std/double"
    },
    {
      "name": "isoLiab",
      "type": "std/double"
    },
    {
      "name": "isoUpl",
      "type": "std/double"
    },
    {
      "name": "liab",
      "type": "std/double"
    },
    {
      "name": "maxLoan",
      "type": "std/double"
    },
    {
      "name": "mgnRatio",
      "type": "std/double"
    },
    {
      "name": "notionalLever",
      "type": "std/double"
    },
    {
      "name": "ordFrozen",
      "type": "std/double"
    },
    {
      "name": "stgyEq",
      "type": "std/double"
    },
    {
      "name": "twap",
      "type": "std/double"
    },
    {
      "name": "uplLib",
      "type": "std/double"
    },
    {
      "name": "upl",
      "type": "std/double"
    },
    {
      "name": "uTime",
      "type": "std/milliseconds"
    },
    {
      "name": "spotInUseAmt",
      "type": "std/double"
    },
    {
      "name": "fixedBal",
      "type": "std/double"
    },
    {
      "name": "borrowFroz",
      "type": "std/double"
    },
    {
      "name": "spotIsoBal",
      "type": "std/double"
    },
    {
      "name": "uplLiab",
      "type": "std/double"
    },
    {
      "name": "imr",
      "type": "std/double"
    },
    {
      "name": "mmr",
      "type": "std/double"
    },
    {
      "name": "rewardBal",
      "type": "std/double"
    },
    {
      "name": "smtSyncEq",
      "type": "std/double"
    },
    {
      "name": "accAvgPx",
      "type": "std/double"
    },
    {
      "name": "autoLendAmt",
      "type": "std/double"
    },
    {
      "name": "autoLendMtAmt",
      "type": "std/double"
    },
    {
      "name": "autoLendStatus",
      "type": "roq/okx/protocol/json/AutoLendStatus"
    },
    {
      "name": "autoStakingStatus",
      "type": "roq/okx/protocol/json/AutoStakingStatus"
    },
    {
      "name": "clSpotInUseAmt",
      "type": "std/double"
    },
    {
      "name": "colBorrAutoConversion",
      "type": "std/double"
    },
    {
      "name": "colRes",
      "type": "std/double"
    },
    {
      "name": "collateralEnabled",
      "type": "std/bool"
    },
    {
      "name": "collateralRestrict",
      "type": "std/bool"
    },
    {
      "name": "frpType",
      "type": "std/double"
    },
    {
      "name": "maxSpotInUseAmt",
      "type": "std/double"
    },
    {
      "name": "openAvgPx",
      "type": "std/double"
    },
    {
      "name": "spotBal",
      "type": "std/double"
    },
    {
      "name": "spotCopyTradingEq",
      "type": "std/double"
    },
    {
      "name": "spotUpl",
      "type": "std/double"
    },
    {
      "name": "spotUplRatio",
      "type": "std/double"
    },
    {
      "name": "totalPnl",
      "type": "std/double"
    },
    {
      "name": "totalPnlRatio",
      "type": "std/double"
    }
  ]
}
